SITH/SITH.py
SITH/SithWriter.py
SITH/Utilities.py
SITH/visualizator.py
SITH/SITH.egg-info/PKG-INFO
SITH/SITH.egg-info/SOURCES.txt
SITH/SITH.egg-info/dependency_links.txt
SITH/SITH.egg-info/requires.txt
SITH/SITH.egg-info/top_level.txt
SITH/__pycache__/SITH.cpython-39.pyc
SITH/__pycache__/SITH_Utilities.cpython-39.pyc
SITH/__pycache__/Sith.cpython-39.pyc
SITH/__pycache__/SithWriter.cpython-39.pyc
SITH/__pycache__/Utilities.cpython-39.pyc
SITH/__pycache__/__init__.cpython-39.pyc
SITH-0.0.10.dist-info/LICENSE
SITH-0.0.10.dist-info/METADATA
SITH-0.0.10.dist-info/WHEEL
SITH-0.0.10.dist-info/top_level.txt
SITH-0.0.10.dist-info/RECORD
