Metadata-Version: 2.1
Name: SITH
Version: 0.0.10
Summary: Stress Induced Traversal of Hessian
Author: Hits_mbm
Author-email: mikaela.farrugia@h-its.org
License: MIT
Classifier: Programming Language :: Python :: 3
Classifier: License :: OSI Approved :: GNU General Public License (GPL)
Classifier: Operating System :: OS Independent
Requires-Python: >=3.9
License-File: LICENSE
Requires-Dist: ase
Requires-Dist: numpy
Requires-Dist: ipywidgets
Requires-Dist: matplotlib
